hej/__init__.py
hej/files/__init__.py
hej/files/__main__.py
hej/files/ops.py
hej-0.1.8.dist-info/LICENSE
hej-0.1.8.dist-info/WHEEL
hej-0.1.8.dist-info/METADATA
hej-0.1.8.dist-info/RECORD
