Metadata-Version: 2.1
Name: hej
Version: 0.1.8
Summary: A collection of useful tools
Home-page: https://github.com/flystarhe/hej
Author: hejian
Author-email: flystarhe@qq.com
Requires-Python: >=3.5
Classifier: License :: OSI Approved :: MIT License
Requires-Dist: simplejson
